calcrule_capitation_payment/__init__.py
calcrule_capitation_payment/admin.py
calcrule_capitation_payment/apps.py
calcrule_capitation_payment/calculation_rule.py
calcrule_capitation_payment/config.py
calcrule_capitation_payment/legacy.py
calcrule_capitation_payment/models.py
calcrule_capitation_payment/tests.py
calcrule_capitation_payment/urls.py
calcrule_capitation_payment/utils.py
calcrule_capitation_payment/views.py
calcrule_capitation_payment/converters/__init__.py
calcrule_capitation_payment/converters/batch_run_to_bill.py
calcrule_capitation_payment/converters/capitation_payment_to_bill_item.py
calcrule_capitation_payment/migrations/0001_initial.py
calcrule_capitation_payment/migrations/0002_delete_capitationpayment.py
calcrule_capitation_payment/migrations/0003_delete_capitationpayment.py
calcrule_capitation_payment/migrations/__init__.py
openimis_be_calcrule_capitation_payment-1.9.1.dist-info/licenses/LICENSE
openimis_be_calcrule_capitation_payment-1.9.1.dist-info/METADATA
openimis_be_calcrule_capitation_payment-1.9.1.dist-info/WHEEL
openimis_be_calcrule_capitation_payment-1.9.1.dist-info/top_level.txt
openimis_be_calcrule_capitation_payment-1.9.1.dist-info/RECORD
